examples/ackley2d_pso.py
examples/ackley2d_pso_profile.py
examples/rosenbrock2d_gd.py
fortoptim/Makefile
fortoptim/__init__.py
fortoptim/compile.py
fortoptim/history_manager.py
fortoptim/problem.py
fortoptim/problems.py
fortoptim/optimizers/__init__.py
fortoptim/optimizers/gradient.py
fortoptim/optimizers/pso.py
fortoptim/optimizers/pso_utils.py
fortoptim/src/__init__.py
fortoptim/src/fortran/gradient_module.f90
fortoptim/src/fortran/pso_utils.f90
fortoptim-0.0.10.dist-info/LICENSE
fortoptim-0.0.10.dist-info/METADATA
fortoptim-0.0.10.dist-info/WHEEL
fortoptim-0.0.10.dist-info/entry_points.txt
fortoptim-0.0.10.dist-info/top_level.txt
fortoptim-0.0.10.dist-info/RECORD
